{
  "date": "2026-04-01",
  "solde": 5.76,
  "mise_du_jour": "1.50",
  "plan": {
    "type": "combine",
    "confiance": "JAUNE",
    "selections": "",
    "cote_totale": "1.89"
  },
  "resultats_veille": "Aucun résultat clair trouvé dans les recherches web pour les matchs d'hier (31 mars 2026) concernant nos paris en attente. Les sources mentionnent des matchs de Champions League avec Liverpool-Chelsea mais sans scores précis correspondant à nos sélections. Tous les paris restent donc EN ATTENTE. Le solde reste inchangé à 7,26€.",
  "stats": {
    "total_paris": 11,
    "paris_gagnes": 1,
    "paris_perdus": 0,
    "taux_reussite": 9.1,
    "roi": 39.7
  }
}